HealthcareAgent/__init__.py
HealthcareAgent/base.py
HealthcareAgent/data_util.py
HealthcareAgent/request_constants.py
HealthcareAgent/request_food_caleries.py
HealthcareAgent-0.0.2.dist-info/METADATA
HealthcareAgent-0.0.2.dist-info/WHEEL
HealthcareAgent-0.0.2.dist-info/top_level.txt
HealthcareAgent-0.0.2.dist-info/RECORD
