Metadata-Version: 2.1
Name: HealthcareAgent
Version: 0.0.2
Summary: Open API of Public Website to get AI Agents in Healthcare Applications
Author-email: aihubadmin@126.com
Project-URL: homepage, http://www.deepnlp.org/search/agent/
Project-URL: repository, https://github.com/AI-Hub-Admin/HealthcareAgent
Keywords: API,Healthcare,AI Agent
Classifier: Development Status :: 3 - Alpha
Classifier: Intended Audience :: Developers
Classifier: Topic :: Software Development :: Build Tools
Classifier: License :: OSI Approved :: MIT License
Requires-Python: >=3.4
